pynxtools/__init__.py
pynxtools/_build_wrapper.py
pynxtools/mkdocs.py
pynxtools/nexus-version.txt
pynxtools/remote_definitions_url.txt
pynxtools/data/201805_WSe2_arpes.nxs
pynxtools/data/NXtest.nxdl.xml
pynxtools/data/NXtest_extended.nxdl.xml
pynxtools/data/xarray_saved_small_calibration.h5
pynxtools/dataconverter/__init__.py
pynxtools/dataconverter/convert.py
pynxtools/dataconverter/exceptions.py
pynxtools/dataconverter/file_hashing.py
pynxtools/dataconverter/hdfdict.py
pynxtools/dataconverter/helpers.py
pynxtools/dataconverter/nexus_tree.py
pynxtools/dataconverter/template.py
pynxtools/dataconverter/validate_file.py
pynxtools/dataconverter/validation.py
pynxtools/dataconverter/writer.py
pynxtools/dataconverter/readers/__init__.py
pynxtools/dataconverter/readers/utils.py
pynxtools/dataconverter/readers/base/__init__.py
pynxtools/dataconverter/readers/base/reader.py
pynxtools/dataconverter/readers/example/__init__.py
pynxtools/dataconverter/readers/example/reader.py
pynxtools/dataconverter/readers/json_map/__init__.py
pynxtools/dataconverter/readers/json_map/reader.py
pynxtools/dataconverter/readers/json_yml/__init__.py
pynxtools/dataconverter/readers/json_yml/reader.py
pynxtools/dataconverter/readers/multi/__init__.py
pynxtools/dataconverter/readers/multi/reader.py
pynxtools/definitions/NXDL_VERSION
pynxtools/definitions/nxdl.xsd
pynxtools/definitions/nxdlTypes.xsd
pynxtools/definitions/applications/NXapm.nxdl.xml
pynxtools/definitions/applications/NXarchive.nxdl.xml
pynxtools/definitions/applications/NXarpes.nxdl.xml
pynxtools/definitions/applications/NXcanSAS.nxdl.xml
pynxtools/definitions/applications/NXdirecttof.nxdl.xml
pynxtools/definitions/applications/NXellipsometry.nxdl.xml
pynxtools/definitions/applications/NXem.nxdl.xml
pynxtools/definitions/applications/NXfluo.nxdl.xml
pynxtools/definitions/applications/NXindirecttof.nxdl.xml
pynxtools/definitions/applications/NXiqproc.nxdl.xml
pynxtools/definitions/applications/NXlauetof.nxdl.xml
pynxtools-0.12.0.dist-info/licenses/LICENSE
pynxtools-0.12.0.dist-info/METADATA
pynxtools-0.12.0.dist-info/WHEEL
pynxtools-0.12.0.dist-info/entry_points.txt
pynxtools-0.12.0.dist-info/top_level.txt
pynxtools-0.12.0.dist-info/RECORD
