Metadata-Version: 2.4
Name: pynxtools
Version: 0.12.0
Summary: Extend NeXus for experiments and characterization in Materials Science and Materials Engineering and serve as a NOMAD parser implementation for NeXus.
Author: The NOMAD Authors
License: 
Project-URL: Homepage, https://github.com/FAIRmat-NFDI/pynxtools
Project-URL: Bug Tracker, https://github.com/FAIRmat-NFDI/pynxtools/issues
Classifier: Programming Language :: Python :: 3.10
Classifier: Programming Language :: Python :: 3.11
Classifier: Programming Language :: Python :: 3.12
Classifier: Programming Language :: Python :: 3.13
Classifier: License :: OSI Approved :: Apache Software License
Classifier: Operating System :: OS Independent
Requires-Python: >=3.10
License-File: LICENSE
Requires-Dist: click>=7.1.2
Requires-Dist: click_default_group
Requires-Dist: h5py>=3.6.0
Requires-Dist: xarray>=0.20.2
Requires-Dist: PyYAML>=6.0
Requires-Dist: numpy
Requires-Dist: pandas>=1.3.2
Requires-Dist: ase>=3.19.0
Requires-Dist: mergedeep
Requires-Dist: importlib-metadata
Requires-Dist: lxml>=4.9.1
Requires-Dist: toposort>=1.10.0
Requires-Dist: anytree
Requires-Dist: pint
Requires-Dist: cachetools
Requires-Dist: structlog
Provides-Extra: docs
Requires-Dist: mkdocs; extra == "docs"
Requires-Dist: markdown-exec[ansi]; extra == "docs"
Requires-Dist: mkdocs-material; extra == "docs"
Requires-Dist: mkdocs-material-extensions; extra == "docs"
Requires-Dist: mkdocs-macros-plugin; extra == "docs"
Requires-Dist: mkdocs-click; extra == "docs"
Requires-Dist: markdown-include; extra == "docs"
Provides-Extra: dev
Requires-Dist: mypy; extra == "dev"
Requires-Dist: ruff>=0.14.0; extra == "dev"
Requires-Dist: pytest; extra == "dev"
Requires-Dist: pytest-timeout; extra == "dev"
Requires-Dist: pytest-cov; extra == "dev"
Requires-Dist: pytest-xdist; extra == "dev"
Requires-Dist: types-pyyaml; extra == "dev"
Requires-Dist: types-pytz; extra == "dev"
Requires-Dist: types-requests; extra == "dev"
Requires-Dist: pre-commit; extra == "dev"
Requires-Dist: debugpy; extra == "dev"
Provides-Extra: convert
Requires-Dist: pynxtools[apm,ellips,em,igor,mpes,raman,spm,xps,xrd]; extra == "convert"
Provides-Extra: apm
Requires-Dist: pynxtools-apm>=0.2.3; extra == "apm"
Provides-Extra: ellips
Requires-Dist: pynxtools-ellips>=0.0.10; extra == "ellips"
Provides-Extra: em
Requires-Dist: pynxtools-em>=0.3.2; extra == "em"
Provides-Extra: igor
Requires-Dist: pynxtools-igor>=0.1.2; extra == "igor"
Provides-Extra: mpes
Requires-Dist: pynxtools-mpes>=0.2.3; extra == "mpes"
Provides-Extra: raman
Requires-Dist: pynxtools-raman>=0.0.11; extra == "raman"
Provides-Extra: spm
Requires-Dist: pynxtools-spm>=0.1.2; extra == "spm"
Provides-Extra: xps
Requires-Dist: pynxtools-xps>=0.5.2; extra == "xps"
Provides-Extra: xrd
Requires-Dist: pynxtools-xrd>=0.0.5; extra == "xrd"
Dynamic: license-file
